Workbook
Name NativeTimeline_Order_Date: #N/A
Name Slicer_Loyalty_Card: #N/A
Name Slicer_Roast_Type_Name: #N/A
Name Slicer_Size: #N/A

Sheet products
A1: Product ID | B1: Coffee Type | C1: Roast Type | D1: Size | E1: Unit Price | F1: Price per 100g | G1: Profit
A2: A-L-0.2 | B2: Ara | C2: L | D2: 0.2 | E2: 3.885 | F2: 1.9425 | G2: 0.34965
A3: A-L-0.5 | B3: Ara | C3: L | D3: 0.5 | E3: 7.77 | F3: 1.554 | G3: 0.6993
A4: A-L-1 | B4: Ara | C4: L | D4: 1 | E4: 12.95 | F4: 1.295 | G4: 1.1655
A5: A-L-2.5 | B5: Ara | C5: L | D5: 2.5 | E5: 29.785 | F5: 1.1914 | G5: 2.68065
A6: A-M-0.2 | B6: Ara | C6: M | D6: 0.2 | E6: 3.375 | F6: 1.6875 | G6: 0.30375
A7: A-M-0.5 | B7: Ara | C7: M | D7: 0.5 | E7: 6.75 | F7: 1.35 | G7: 0.6075
A8: A-M-1 | B8: Ara | C8: M | D8: 1 | E8: 11.25 | F8: 1.125 | G8: 1.0125
A9: A-M-2.5 | B9: Ara | C9: M | D9: 2.5 | E9: 25.875 | F9: 1.035 | G9: 2.32875
A10: A-D-0.2 | B10: Ara | C10: D | D10: 0.2 | E10: 2.985 | F10: 1.4925 | G10: 0.26865
A11: A-D-0.5 | B11: Ara | C11: D | D11: 0.5 | E11: 5.97 | F11: 1.194 | G11: 0.5373
A12: A-D-1 | B12: Ara | C12: D | D12: 1 | E12: 9.95 | F12: 0.995 | G12: 0.8955
A13: A-D-2.5 | B13: Ara | C13: D | D13: 2.5 | E13: 22.885 | F13: 0.9154 | G13: 2.05965
... A49: E-D-2.5 | B49: Exc | C49: D | D49: 2.5 | E49: 27.945 | F49: 1.1178 | G49: 3.07395

Sheet customers
A1: Customer ID | B1: Customer Name | C1: Email | D1: Phone Number | E1: Address Line 1 | F1: City | G1: Country | H1: Postcode | I1: Loyalty Card
A2: 17670-51384-MA | B2: Aloisia Allner | C2: aallner0@lulu.com | D2: +1 (862) 817-0124 | E2: 57999 Pepper Wood Alley | F2: Paterson | G2: United States | H2: 7505 | I2: Yes
A3: 73342-18763-UW | B3: Piotr Bote | C3: pbote1@yelp.com | D3: +353 (913) 396-4653 | E3: 2112 Ridgeway Hill | F3: Crumlin | G3: Ireland | H3: D6W | I3: No
A4: 21125-22134-PX | B4: Jami Redholes | C4: jredholes2@tmall.com | D4: +1 (210) 986-6806 | E4: 5214 Bartillon Park | F4: San Antonio | G4: United States | H4: 78205 | I4: Yes
A5: 71253-00052-RN | B5: Dene Azema | C5: dazema3@facebook.com | D5: +1 (217) 418-0714 | E5: 27 Maywood Place | F5: Springfield | G5: United States | H5: 62711 | I5: Yes
A6: 23806-46781-OU | B6: Christoffer O' Shea | D6: +353 (698) 362-9201 | E6: 38980 Manitowish Junction | F6: Cill Airne | G6: Ireland | H6: N41 | I6: No
A7: 86561-91660-RB | B7: Beryle Cottier | D7: +1 (570) 289-7473 | E7: 2651 Stoughton Place | F7: Scranton | G7: United States | H7: 18505 | I7: No
A8: 65223-29612-CB | B8: Shaylynn Lobe | C8: slobe6@nifty.com | D8: +1 (937) 954-4541 | E8: 7005 Mariners Cove Place | F8: Dayton | G8: United States | H8: 45440 | I8: Yes
A9: 21134-81676-FR | B9: Melvin Wharfe | D9: +353 (507) 574-3034 | E9: 7 Straubel Road | F9: Kill | G9: Ireland | H9: P24 | I9: Yes
A10: 03396-68805-ZC | B10: Guthrey Petracci | C10: gpetracci8@livejournal.com | D10: +1 (310) 868-1842 | E10: 949 Paget Parkway | F10: Los Angeles | G10: United States | H10: 90045 | I10: No
A11: 61021-27840-ZN | B11: Rodger Raven | C11: rraven9@ed.gov | D11: +1 (213) 263-0288 | E11: 1 Reinke Avenue | F11: Los Angeles | G11: United States | H11: 90065 | I11: No
A12: 76239-90137-UQ | B12: Ferrell Ferber | C12: fferbera@businesswire.com | D12: +1 (408) 383-5302 | E12: 68 High Crossing Court | F12: San Jose | G12: United States | H12: 95160 | I12: No
A13: 49315-21985-BB | B13: Duky Phizackerly | C13: dphizackerlyb@utexas.edu | D13: +1 (408) 533-6012 | E13: 28643 Bluejay Crossing | F13: San Jose | G13: United States | H13: 95194 | I13: Yes
A14: 34136-36674-OM | B14: Rosaleen Scholar | C14: rscholarc@nyu.edu | D14: +1 (804) 420-0420 | E14: 80915 Montana Park | F14: Richmond | G14: United States | H14: 23285 | I14: No
A15: 39396-12890-PE | B15: Terence Vanyutin | C15: tvanyutind@wix.com | E15: 331 Bunting Hill | F15: Migrate | G15: United States | H15: 41905 | I15: No
A16: 95875-73336-RG | B16: Patrice Trobe | C16: ptrobee@wunderground.com | D16: +1 (314) 240-7896 | E16: 827 Declaration Plaza | F16: Saint Louis | G16: United States | H16: 63131 | I16: Yes
A17: 25473-43727-BY | B17: Llywellyn Oscroft | C17: loscroftf@ebay.co.uk | E17: 022 Roth Place | F17: Philadelphia | G17: United States | H17: 19172 | I17: No
A18: 99643-51048-IQ | B18: Minni Alabaster | C18: malabasterg@hexun.com | D18: +1 (971) 483-6255 | E18: 3 Charing Cross Trail | F18: Portland | G18: United States | H18: 97271 | I18: No
A19: 62173-15287-CU | B19: Rhianon Broxup | C19: rbroxuph@jimdo.com | D19: +1 (713) 663-1338 | E19: 83517 Thierer Court | F19: Houston | G19: United States | H19: 77240 | I19: No
A20: 57611-05522-ST | B20: Pall Redford | C20: predfordi@ow.ly | E20: 7337 Hayes Junction | F20: Caherconlish | G20: Ireland | H20: F45 | I20: Yes
A21: 76664-37050-DT | B21: Aurea Corradino | C21: acorradinoj@harvard.edu | D21: +1 (646) 202-5965 | E21: 698 Canary Terrace | F21: New York City | G21: United States | H21: 10060 | I21: Yes
A22: 84565-53984-SX | B22: Kendal Scardefield | D22: +353 (733) 405-3302 | E22: 3 Northridge Crossing | F22: Clondalkin | G22: Ireland | H22: D24 | I22: Yes
A23: 03090-88267-BQ | B23: Avrit Davidowsky | C23: adavidowskyl@netvibes.com | D23: +1 (616) 481-9962 | E23: 9 Warrior Junction | F23: Grand Rapids | G23: United States | H23: 49560 | I23: No
A24: 37651-47492-NC | B24: Annabel Antuk | C24: aantukm@kickstarter.com | D24: +1 (941) 740-6268 | E24: 77965 Lawn Park | F24: Punta Gorda | G24: United States | H24: 33982 | I24: Yes
A25: 95399-57205-HI | B25: Iorgo Kleinert | C25: ikleinertn@timesonline.co.uk | D25: +1 (360) 352-6598 | E25: 1 Morningstar Lane | F25: Vancouver | G25: United States | H25: 98682 | I25: Yes
A26: 24010-66714-HW | B26: Chrisy Blofeld | C26: cblofeldo@amazon.co.uk | D26: +1 (303) 936-3357 | E26: 013 Talisman Terrace | F26: Englewood | G26: United States | H26: 80150 | I26: No
A27: 07591-92789-UA | B27: Culley Farris | D27: +1 (941) 267-4822 | E27: 4 Mitchell Drive | F27: Punta Gorda | G27: United States | H27: 33982 | I27: Yes
A28: 49231-44455-IC | B28: Selene Shales | C28: sshalesq@umich.edu | D28: +1 (707) 881-5004 | E28: 74 Bultman Plaza | F28: Petaluma | G28: United States | H28: 94975 | I28: Yes
A29: 50124-88608-EO | B29: Vivie Danneil | C29: vdanneilr@mtv.com | D29: +353 (751) 346-0399 | E29: 5626 Darwin Avenue | F29: Tralee | G29: Ireland | H29: V92 | I29: No
A30: 00888-74814-UZ | B30: Theresita Newbury | C30: tnewburys@usda.gov | D30: +353 (803) 587-0026 | E30: 79526 Bultman Lane | F30: Clonskeagh | G30: Ireland | H30: D04 | I30: No
A31: 14158-30713-OB | B31: Mozelle Calcutt | C31: mcalcuttt@baidu.com | D31: +353 (928) 869-1762 | E31: 4389 Russell Way | F31: Rathwire | G31: Ireland | H31: Y25 | I31: Yes
A32: 51427-89175-QJ | B32: Adrian Swaine | D32: +1 (303) 486-9517 | E32: 95 Straubel Hill | F32: Aurora | G32: United States | H32: 80044 | I32: No
A33: 52082-49024-ON | B33: Ray Leivesley | C33: rleivesleyv@canalblog.com | D33: +1 (212) 535-7791 | E33: 91 Stephen Drive | F33: Jamaica | G33: United States | H33: 11407 | I33: No
A34: 04540-43685-DV | B34: Nelly Basezzi | C34: nbasezziw@webeden.co.uk | D34: +353 (125) 815-7345 | E34: 923 Mallard Junction | F34: Bailieborough | G34: Ireland | H34: C15 | I34: Yes
A35: 39123-12846-YJ | B35: Gallard Gatheral | C35: ggatheralx@123-reg.co.uk | E35: 40 Clemons Place | F35: Grand Forks | G35: United States | H35: 58207 | I35: No
A36: 44981-99666-XB | B36: Una Welberry | C36: uwelberryy@ebay.co.uk | D36: +44 (392) 503-8132 | E36: 40915 Schlimgen Park | F36: Upton | G36: United Kingdom | H36: DN21 | I36: Yes
A37: 24825-51803-CQ | B37: Faber Eilhart | C37: feilhartz@who.int | D37: +1 (304) 510-6095 | E37: 6966 Victoria Street | F37: Charleston | G37: United States | H37: 25362 | I37: No
A38: 77634-13918-GJ | B38: Zorina Ponting | C38: zponting10@altervista.org | D38: +1 (501) 172-1476 | E38: 7118 Holmberg Court | F38: Little Rock | G38: United States | H38: 72204 | I38: No
A39: 13694-25001-LX | B39: Silvio Strase | C39: sstrase11@booking.com | D39: +1 (303) 579-8015 | E39: 5 Forest Lane | F39: Denver | G39: United States | H39: 80291 | I39: No
A40: 08523-01791-TI | B40: Dorie de la Tremoille | C40: dde12@unesco.org | D40: +1 (612) 492-5160 | E40: 0817 Dennis Street | F40: Minneapolis | G40: United States | H40: 55458 | I40: No
A41: 49860-68865-AB | B41: Hy Zanetto | E41: 469 Paget Place | F41: Tucson | G41: United States | H41: 85715 | I41: Yes
A42: 21240-83132-SP | B42: Jessica McNess | D42: +1 (504) 545-1478 | E42: 664 Erie Place | F42: New Orleans | G42: United States | H42: 70116 | I42: No
A43: 08350-81623-TF | B43: Lorenzo Yeoland | C43: lyeoland15@pbs.org | D43: +1 (860) 576-2887 | E43: 8510 Merrick Road | F43: Hartford | G43: United States | H43: 6183 | I43: Yes
A44: 73284-01385-SJ | B44: Abigail Tolworthy | C44: atolworthy16@toplist.cz | D44: +1 (801) 722-4425 | E44: 74 Shopko Way | F44: Ogden | G44: United States | H44: 84409 | I44: Yes
A45: 04152-34436-IE | B45: Maurie Bartol | D45: +1 (617) 493-7594 | E45: 7625 Starling Court | F45: Boston | G45: United States | H45: 2216 | I45: No
A46: 06631-86965-XP | B46: Olag Baudassi | C46: obaudassi18@seesaa.net | D46: +1 (585) 356-6251 | E46: 55 Dottie Court | F46: Rochester | G46: United States | H46: 14604 | I46: Yes
A47: 54619-08558-ZU | B47: Petey Kingsbury | C47: pkingsbury19@comcast.net | D47: +1 (917) 705-8224 | E47: 28 Loftsgordon Place | F47: Bronx | G47: United States | H47: 10469 | I47: No
A48: 85589-17020-CX | B48: Donna Baskeyfied | D48: +1 (205) 923-1460 | E48: 7586 Logan Avenue | F48: Birmingham | G48: United States | H48: 35205 | I48: Yes
A49: 36078-91009-WU | B49: Arda Curley | C49: acurley1b@hao123.com | D49: +1 (760) 840-3808 | E49: 45098 Scott Drive | F49: San Bernardino | G49: United States | H49: 92415 | I49: Yes
A50: 15770-27099-GX | B50: Raynor McGilvary | C50: rmcgilvary1c@tamu.edu | E50: 496 Rockefeller Court | F50: Norfolk | G50: United States | H50: 23514 | I50: No
A51: 91460-04823-BX | B51: Isis Pikett | C51: ipikett1d@xinhuanet.com | D51: +1 (202) 871-9039 | E51: 5892 Hauk Drive | F51: Washington | G51: United States | H51: 20409 | I51: No
A52: 45089-52817-WN | B52: Inger Bouldon | C52: ibouldon1e@gizmodo.com | D52: +1 (754) 391-4736 | E52: 925 Barby Circle | F52: Fort Lauderdale | G52: United States | H52: 33355 | I52: No
A53: 76447-50326-IC | B53: Karry Flanders | C53: kflanders1f@over-blog.com | D53: +353 (467) 720-7274 | E53: 88 Blue Bill Park Avenue | F53: Crumlin | G53: Ireland | H53: D6W | I53: Yes
A54: 26333-67911-OL | B54: Hartley Mattioli | C54: hmattioli1g@webmd.com | E54: 126 Valley Edge Street | F54: Kinloch | G54: United Kingdom | H54: PH43 | I54: No
A55: 40768-49176-BL | B55: Horatio Rubberts | C55: hrubberts1h@google.com.hk | D55: +1 (801) 635-8791 | E55: 459 Russell Center | F55: Provo | G55: United States | H55: 84605 | I55: No
A56: 22107-86640-SB | B56: Archambault Gillard | C56: agillard1i@issuu.com | D56: +1 (419) 663-2236 | E56: 97490 Susan Avenue | F56: Toledo | G56: United States | H56: 43666 | I56: No
A57: 09960-34242-LZ | B57: Salomo Cushworth | D57: +1 (609) 409-7044 | E57: 44 Oneill Parkway | F57: Trenton | G57: United States | H57: 8650 | I57: No
A58: 04671-85591-RT | B58: Theda Grizard | C58: tgrizard1k@odnoklassniki.ru | D58: +1 (813) 243-2150 | E58: 6 Knutson Pass | F58: Tampa | G58: United States | H58: 33686 | I58: Yes
A59: 25729-68859-UA | B59: Rozele Relton | C59: rrelton1l@stanford.edu | D59: +1 (850) 626-1181 | E59: 2484 Reindahl Court | F59: Pensacola | G59: United States | H59: 32590 | I59: No
A60: 05501-86351-NX | B60: Willa Rolling | D60: +1 (813) 759-3534 | E60: 3 Mockingbird Plaza | F60: Zephyrhills | G60: United States | H60: 33543 | I60: Yes
A61: 04521-04300-OK | B61: Stanislaus Gilroy | C61: sgilroy1n@eepurl.com | E61: 9120 Harbort Terrace | F61: Saint Paul | G61: United States | H61: 55123 | I61: Yes
A62: 58689-55264-VK | B62: Correy Cottingham | C62: ccottingham1o@wikipedia.org | D62: +1 (260) 764-1820 | E62: 394 Logan Road | F62: Fort Wayne | G62: United States | H62: 46862 | I62: No
A63: 79436-73011-MM | B63: Pammi Endacott | D63: +44 (177) 260-5076 | E63: 5841 Atwood Lane | F63: Wootton | G63: United Kingdom | H63: NN4 | I63: Yes
A64: 65552-60476-KY | B64: Nona Linklater | D64: +1 (239) 347-9766 | E64: 856 Bonner Parkway | F64: Naples | G64: United States | H64: 34114 | I64: Yes
A65: 69904-02729-YS | B65: Annadiane Dykes | C65: adykes1r@eventbrite.com | D65: +1 (312) 111-6203 | E65: 31 Northport Terrace | F65: Chicago | G65: United States | H65: 60681 | I65: No
A66: 01433-04270-AX | B66: Felecia Dodgson | D66: +1 (973) 434-8662 | E66: 48053 8th Crossing | F66: Newark | G66: United States | H66: 7104 | I66: Yes
A67: 14204-14186-LA | B67: Angelia Cockrem | C67: acockrem1t@engadget.com | D67: +1 (571) 316-8217 | E67: 1 Sherman Alley | F67: Vienna | G67: United States | H67: 22184 | I67: Yes
A68: 32948-34398-HC | B68: Belvia Umpleby | C68: bumpleby1u@soundcloud.com | D68: +1 (682) 627-0888 | E68: 710 Prairie Rose Terrace | F68: Fort Worth | G68: United States | H68: 76178 | I68: Yes
A69: 77343-52608-FF | B69: Nat Saleway | C69: nsaleway1v@dedecms.com | D69: +1 (323) 473-0294 | E69: 0780 Anthes Plaza | F69: Burbank | G69: United States | H69: 91505 | I69: No
A70: 42770-36274-QA | B70: Hayward Goulter | C70: hgoulter1w@abc.net.au | D70: +1 (423) 764-7751 | E70: 2081 Mariners Cove Drive | F70: Kingsport | G70: United States | H70: 37665 | I70: No
A71: 14103-58987-ZU | B71: Gay Rizzello | C71: grizzello1x@symantec.com | D71: +44 (247) 225-8003 | E71: 21 Schmedeman Crossing | F71: Liverpool | G71: United Kingdom | H71: L33 | I71: Yes
A72: 69958-32065-SW | B72: Shannon List | C72: slist1y@mapquest.com | D72: +1 (614) 279-9816 | E72: 7123 Algoma Center | F72: Columbus | G72: United States | H72: 43231 | I72: No
A73: 69533-84907-FA | B73: Shirlene Edmondson | C73: sedmondson1z@theguardian.com | D73: +353 (248) 428-7978 | E73: 4752 International Point | F73: Newmarket on Fergus | G73: Ireland | H73: P17 | I73: No
A74: 76005-95461-CI | B74: Aurlie McCarl | D74: +1 (504) 209-2724 | E74: 731 David Park | F74: New Orleans | G74: United States | H74: 70183 | I74: No
A75: 15395-90855-VB | B75: Alikee Carryer | D75: +1 (704) 799-5219 | E75: 247 Helena Drive | F75: Charlotte | G75: United States | H75: 28230 | I75: Yes
A76: 80640-45811-LB | B76: Jennifer Rangall | C76: jrangall22@newsvine.com | D76: +1 (781) 512-6637 | E76: 0 Grasskamp Lane | F76: Springfield | G76: United States | H76: 1114 | I76: Yes
A77: 28476-04082-GR | B77: Kipper Boorn | C77: kboorn23@ezinearticles.com | D77: +353 (359) 134-1550 | E77: 9513 Meadow Ridge Parkway | F77: Listowel | G77: Ireland | H77: V31 | I77: Yes
A78: 12018-75670-EU | B78: Melania Beadle | D78: +353 (569) 458-9673 | E78: 4418 Quincy Terrace | F78: Moycullen | G78: Ireland | H78: A41 | I78: Yes
A79: 86437-17399-FK | B79: Colene Elgey | C79: celgey25@webs.com | D79: +1 (432) 261-0702 | E79: 45 Marcy Crossing | F79: Midland | G79: United States | H79: 79705 | I79: No
A80: 62979-53167-ML | B80: Lothaire Mizzi | C80: lmizzi26@rakuten.co.jp | D80: +1 (214) 719-8530 | E80: 74 Atwood Lane | F80: Dallas | G80: United States | H80: 75323 | I80: Yes
A81: 54810-81899-HL | B81: Cletis Giacomazzo | C81: cgiacomazzo27@jigsy.com | D81: +1 (571) 703-2064 | E81: 817 Ridgeway Hill | F81: Dulles | G81: United States | H81: 20189 | I81: No
A82: 26103-41504-IB | B82: Ami Arnow | C82: aarnow28@arizona.edu | D82: +1 (650) 238-1964 | E82: 12 Oakridge Court | F82: Oakland | G82: United States | H82: 94627 | I82: Yes
A83: 76534-45229-SG | B83: Sheppard Yann | C83: syann29@senate.gov | D83: +1 (719) 803-5276 | E83: 4 Farmco Place | F83: Colorado Springs | G83: United States | H83: 80930 | I83: Yes
A84: 81744-27332-RR | B84: Bunny Naulls | C84: bnaulls2a@tiny.cc | D84: +353 (809) 128-0755 | E84: 595 Melby Avenue | F84: Adare | G84: Ireland | H84: H54 | I84: Yes
A85: 91513-75657-PH | B85: Hally Lorait | D85: +1 (716) 869-3749 | E85: 80 Jana Avenue | F85: Buffalo | G85: United States | H85: 14205 | I85: Yes
A86: 30373-66619-CB | B86: Zaccaria Sherewood | C86: zsherewood2c@apache.org | D86: +1 (209) 433-7924 | E86: 1325 Jay Terrace | F86: Fresno | G86: United States | H86: 93715 | I86: No
A87: 31582-23562-FM | B87: Jeffrey Dufaire | C87: jdufaire2d@fc2.com | E87: 8 Buell Junction | F87: Fort Worth | G87: United States | H87: 76121 | I87: No
A88: 58638-01029-CB | B88: Blancha McAmish | C88: bmcamish2e@tripadvisor.com | E88: 5484 Stephen Court | F88: Oklahoma City | G88: United States | H88: 73179 | I88: Yes
A89: 81431-12577-VD | B89: Beitris Keaveney | C89: bkeaveney2f@netlog.com | E89: 67319 Redwing Parkway | F89: Beaumont | G89: United States | H89: 77705 | I89: No
A90: 68894-91205-MP | B90: Elna Grise | C90: egrise2g@cargocollective.com | E90: 92 Becker Circle | F90: Reno | G90: United States | H90: 89519 | I90: No
A91: 87602-55754-VN | B91: Torie Gottelier | C91: tgottelier2h@vistaprint.com | D91: +1 (816) 743-8492 | E91: 426 Division Avenue | F91: Kansas City | G91: United States | H91: 64136 | I91: No
A92: 39181-35745-WH | B92: Loydie Langlais | D92: +353 (576) 222-5069 | E92: 290 Ilene Street | F92: Crumlin | G92: Ireland | H92: D6W | I92: Yes
A93: 30381-64762-NG | B93: Adham Greenhead | C93: agreenhead2j@dailymail.co.uk | D93: +1 (951) 797-0738 | E93: 0062 Spenser Place | F93: Corona | G93: United States | H93: 92878 | I93: No
A94: 17503-27693-ZH | B94: Hamish MacSherry | D94: +1 (512) 430-4374 | E94: 7 Brentwood Plaza | F94: Austin | G94: United States | H94: 78759 | I94: Yes
A95: 89442-35633-HJ | B95: Else Langcaster | C95: elangcaster2l@spotify.com | D95: +44 (547) 590-3103 | E95: 3658 Jenna Street | F95: Normanton | G95: United Kingdom | H95: LE15 | I95: Yes
A96: 13654-85265-IL | B96: Rudy Farquharson | E96: 30178 Claremont Road | F96: Charlesland | G96: Ireland | H96: A63 | I96: Yes
A97: 40946-22090-FP | B97: Norene Magauran | C97: nmagauran2n@51.la | E97: 567 Artisan Place | F97: Fresno | G97: United States | H97: 93762 | I97: No
A98: 29050-93691-TS | B98: Vicki Kirdsch | C98: vkirdsch2o@google.fr | E98: 0263 Golf Street | F98: Saint Louis | G98: United States | H98: 63150 | I98: No
A99: 64395-74865-WF | B99: Ilysa Whapple | C99: iwhapple2p@com.com | D99: +1 (559) 522-1152 | E99: 41598 Everett Drive | F99: Fresno | G99: United States | H99: 93726 | I99: No
A100: 81861-66046-SU | B100: Ruy Cancellieri | D100: +353 (338) 743-8327 | E100: 251 Welch Parkway | F100: Confey | G100: Ireland | H100: A86 | I100: No
...

Sheet orders_final
A1: Order ID | B1: Order Date | C1: Customer ID | D1: Product ID | E1: Quantity | F1: Customer Name | G1: Email | H1: Country | I1: Coffee Type | J1: Roast Type | K1: Size | L1: Unit Price | M1: Sales | N1: Coffee Type Name | O1: Roast Type Name | P1: Loyalty Card
A2: QEV-37451-860 | B2: 43713 | C2: 17670-51384-MA | D2: R-M-1 | E2: 2 | F2: Aloisia Allner | G2: aallner0@lulu.com | H2: United States | I2: Rob | J2: M | K2: 1 | L2: 9.95 | M2: 19.9 | N2: Robusta | O2: Medium | P2: =_xlfn.XLOOKUP(orders_final[[#This Row],[Customer ID]], customers!$A$1:$A$1001, customers!$I$1:$I$1001, 0) -> Yes
A3: QEV-37451-860 | B3: 43713 | C3: 17670-51384-MA | D3: E-M-0.5 | E3: 5 | F3: Aloisia Allner | G3: aallner0@lulu.com | H3: United States | I3: Exc | J3: M | K3: 0.5 | L3: 8.25 | M3: 41.25 | N3: Excelsa | O3: Medium | P3: =_xlfn.XLOOKUP(orders_final[[#This Row],[Customer ID]], customers!$A$1:$A$1001, customers!$I$1:$I$1001, 0) -> Yes
A4: FAA-43335-268 | B4: 44364 | C4: 21125-22134-PX | D4: A-L-1 | E4: 1 | F4: Jami Redholes | G4: jredholes2@tmall.com | H4: United States | I4: Ara | J4: L | K4: 1 | L4: 12.95 | M4: 12.95 | N4: Arabica | O4: Light | P4: =_xlfn.XLOOKUP(orders_final[[#This Row],[Customer ID]], customers!$A$1:$A$1001, customers!$I$1:$I$1001, 0) -> Yes
A5: KAC-83089-793 | B5: 44392 | C5: 23806-46781-OU | D5: E-M-1 | E5: 2 | F5: Christoffer O' Shea | H5: Ireland | I5: Exc | J5: M | K5: 1 | L5: 13.75 | M5: 27.5 | N5: Excelsa | O5: Medium | P5: =_xlfn.XLOOKUP(orders_final[[#This Row],[Customer ID]], customers!$A$1:$A$1001, customers!$I$1:$I$1001, 0) -> No
A6: KAC-83089-793 | B6: 44392 | C6: 23806-46781-OU | D6: R-L-2.5 | E6: 2 | F6: Christoffer O' Shea | H6: Ireland | I6: Rob | J6: L | K6: 2.5 | L6: 27.485 | M6: 54.97 | N6: Robusta | O6: Light | P6: =_xlfn.XLOOKUP(orders_final[[#This Row],[Customer ID]], customers!$A$1:$A$1001, customers!$I$1:$I$1001, 0) -> No
A7: CVP-18956-553 | B7: 44412 | C7: 86561-91660-RB | D7: L-D-1 | E7: 3 | F7: Beryle Cottier | H7: United States | I7: Lib | J7: D | K7: 1 | L7: 12.95 | M7: 38.85 | N7: Liberica | O7: Dark | P7: =_xlfn.XLOOKUP(orders_final[[#This Row],[Customer ID]], customers!$A$1:$A$1001, customers!$I$1:$I$1001, 0) -> No
A8: IPP-31994-879 | B8: 44582 | C8: 65223-29612-CB | D8: E-D-0.5 | E8: 3 | F8: Shaylynn Lobe | G8: slobe6@nifty.com | H8: United States | I8: Exc | J8: D | K8: 0.5 | L8: 7.29 | M8: 21.87 | N8: Excelsa | O8: Dark | P8: =_xlfn.XLOOKUP(orders_final[[#This Row],[Customer ID]], customers!$A$1:$A$1001, customers!$I$1:$I$1001, 0) -> Yes
A9: SNZ-65340-705 | B9: 44701 | C9: 21134-81676-FR | D9: L-L-0.2 | E9: 1 | F9: Melvin Wharfe | H9: Ireland | I9: Lib | J9: L | K9: 0.2 | L9: 4.755 | M9: 4.755 | N9: Liberica | O9: Light | P9: =_xlfn.XLOOKUP(orders_final[[#This Row],[Customer ID]], customers!$A$1:$A$1001, customers!$I$1:$I$1001, 0) -> Yes
A10: EZT-46571-659 | B10: 43467 | C10: 03396-68805-ZC | D10: R-M-0.5 | E10: 3 | F10: Guthrey Petracci | G10: gpetracci8@livejournal.com | H10: United States | I10: Rob | J10: M | K10: 0.5 | L10: 5.97 | M10: 17.91 | N10: Robusta | O10: Medium | P10: =_xlfn.XLOOKUP(orders_final[[#This Row],[Customer ID]], customers!$A$1:$A$1001, customers!$I$1:$I$1001, 0) -> No
A11: NWQ-70061-912 | B11: 43713 | C11: 61021-27840-ZN | D11: R-M-0.5 | E11: 1 | F11: Rodger Raven | G11: rraven9@ed.gov | H11: United States | I11: Rob | J11: M | K11: 0.5 | L11: 5.97 | M11: 5.97 | N11: Robusta | O11: Medium | P11: =_xlfn.XLOOKUP(orders_final[[#This Row],[Customer ID]], customers!$A$1:$A$1001, customers!$I$1:$I$1001, 0) -> No
A12: BKK-47233-845 | B12: 44263 | C12: 76239-90137-UQ | D12: A-D-1 | E12: 4 | F12: Ferrell Ferber | G12: fferbera@businesswire.com | H12: United States | I12: Ara | J12: D | K12: 1 | L12: 9.95 | M12: 39.8 | N12: Arabica | O12: Dark | P12: =_xlfn.XLOOKUP(orders_final[[#This Row],[Customer ID]], customers!$A$1:$A$1001, customers!$I$1:$I$1001, 0) -> No
A13: VQR-01002-970 | B13: 44132 | C13: 49315-21985-BB | D13: E-L-2.5 | E13: 5 | F13: Duky Phizackerly | G13: dphizackerlyb@utexas.edu | H13: United States | I13: Exc | J13: L | K13: 2.5 | L13: 34.155 | M13: 170.775 | N13: Excelsa | O13: Light | P13: =_xlfn.XLOOKUP(orders_final[[#This Row],[Customer ID]], customers!$A$1:$A$1001, customers!$I$1:$I$1001, 0) -> Yes
A14: SZW-48378-399 | B14: 44744 | C14: 34136-36674-OM | D14: R-M-1 | E14: 5 | F14: Rosaleen Scholar | G14: rscholarc@nyu.edu | H14: United States | I14: Rob | J14: M | K14: 1 | L14: 9.95 | M14: 49.75 | N14: Robusta | O14: Medium | P14: =_xlfn.XLOOKUP(orders_final[[#This Row],[Customer ID]], customers!$A$1:$A$1001, customers!$I$1:$I$1001, 0) -> No
A15: ITA-87418-783 | B15: 43973 | C15: 39396-12890-PE | D15: R-D-2.5 | E15: 2 | F15: Terence Vanyutin | G15: tvanyutind@wix.com | H15: United States | I15: Rob | J15: D | K15: 2.5 | L15: 20.585 | M15: 41.17 | N15: Robusta | O15: Dark | P15: =_xlfn.XLOOKUP(orders_final[[#This Row],[Customer ID]], customers!$A$1:$A$1001, customers!$I$1:$I$1001, 0) -> No
A16: GNZ-46006-527 | B16: 44656 | C16: 95875-73336-RG | D16: L-D-0.2 | E16: 3 | F16: Patrice Trobe | G16: ptrobee@wunderground.com | H16: United States | I16: Lib | J16: D | K16: 0.2 | L16: 3.885 | M16: 11.655 | N16: Liberica | O16: Dark | P16: =_xlfn.XLOOKUP(orders_final[[#This Row],[Customer ID]], customers!$A$1:$A$1001, customers!$I$1:$I$1001, 0) -> Yes
A17: FYQ-78248-319 | B17: 44719 | C17: 25473-43727-BY | D17: R-M-2.5 | E17: 5 | F17: Llywellyn Oscroft | G17: loscroftf@ebay.co.uk | H17: United States | I17: Rob | J17: M | K17: 2.5 | L17: 22.885 | M17: 114.425 | N17: Robusta | O17: Medium | P17: =_xlfn.XLOOKUP(orders_final[[#This Row],[Customer ID]], customers!$A$1:$A$1001, customers!$I$1:$I$1001, 0) -> No
A18: VAU-44387-624 | B18: 43544 | C18: 99643-51048-IQ | D18: A-M-0.2 | E18: 6 | F18: Minni Alabaster | G18: malabasterg@hexun.com | H18: United States | I18: Ara | J18: M | K18: 0.2 | L18: 3.375 | M18: 20.25 | N18: Arabica | O18: Medium | P18: =_xlfn.XLOOKUP(orders_final[[#This Row],[Customer ID]], customers!$A$1:$A$1001, customers!$I$1:$I$1001, 0) -> No
A19: RDW-33155-159 | B19: 43757 | C19: 62173-15287-CU | D19: A-L-1 | E19: 6 | F19: Rhianon Broxup | G19: rbroxuph@jimdo.com | H19: United States | I19: Ara | J19: L | K19: 1 | L19: 12.95 | M19: 77.7 | N19: Arabica | O19: Light | P19: =_xlfn.XLOOKUP(orders_final[[#This Row],[Customer ID]], customers!$A$1:$A$1001, customers!$I$1:$I$1001, 0) -> No
A20: TDZ-59011-211 | B20: 43629 | C20: 57611-05522-ST | D20: R-D-2.5 | E20: 4 | F20: Pall Redford | G20: predfordi@ow.ly | H20: Ireland | I20: Rob | J20: D | K20: 2.5 | L20: 20.585 | M20: 82.34 | N20: Robusta | O20: Dark | P20: =_xlfn.XLOOKUP(orders_final[[#This Row],[Customer ID]], customers!$A$1:$A$1001, customers!$I$1:$I$1001, 0) -> Yes
A21: IDU-25793-399 | B21: 44169 | C21: 76664-37050-DT | D21: A-M-0.2 | E21: 5 | F21: Aurea Corradino | G21: acorradinoj@harvard.edu | H21: United States | I21: Ara | J21: M | K21: 0.2 | L21: 3.375 | M21: 16.875 | N21: Arabica | O21: Medium | P21: =_xlfn.XLOOKUP(orders_final[[#This Row],[Customer ID]], customers!$A$1:$A$1001, customers!$I$1:$I$1001, 0) -> Yes
... A26: TKY-71558-096 | B26: 44454 | C26: 24010-66714-HW | D26: A-M-1 | E26: 1 | F26: Chrisy Blofeld | G26: cblofeldo@amazon.co.uk | H26: United States | I26: Ara | J26: M | K26: 1 | L26: 11.25 | M26: 11.25 | N26: Arabica | O26: Medium | P26: =_xlfn.XLOOKUP(orders_final[[#This Row],[Customer ID]], customers!$A$1:$A$1001, customers!$I$1:$I$1001, 0) -> No
A27: OXY-65322-253 | B27: 44128 | C27: 07591-92789-UA | D27: E-M-0.2 | E27: 3 | F27: Culley Farris | H27: United States | I27: Exc | J27: M | K27: 0.2 | L27: 4.125 | M27: 12.375 | N27: Excelsa | O27: Medium | P27: =_xlfn.XLOOKUP(orders_final[[#This Row],[Customer ID]], customers!$A$1:$A$1001, customers!$I$1:$I$1001, 0) -> Yes
A28: EVP-43500-491 | B28: 43516 | C28: 49231-44455-IC | D28: A-M-0.5 | E28: 4 | F28: Selene Shales | G28: sshalesq@umich.edu | H28: United States | I28: Ara | J28: M | K28: 0.5 | L28: 6.75 | M28: 27 | N28: Arabica | O28: Medium | P28: =_xlfn.XLOOKUP(orders_final[[#This Row],[Customer ID]], customers!$A$1:$A$1001, customers!$I$1:$I$1001, 0) -> Yes
A29: WAG-26945-689 | B29: 43746 | C29: 50124-88608-EO | D29: A-M-0.2 | E29: 5 | F29: Vivie Danneil | G29: vdanneilr@mtv.com | H29: Ireland | I29: Ara | J29: M | K29: 0.2 | L29: 3.375 | M29: 16.875 | N29: Arabica | O29: Medium | P29: =_xlfn.XLOOKUP(orders_final[[#This Row],[Customer ID]], customers!$A$1:$A$1001, customers!$I$1:$I$1001, 0) -> No
A30: CHE-78995-767 | B30: 44775 | C30: 00888-74814-UZ | D30: A-D-0.5 | E30: 3 | F30: Theresita Newbury | G30: tnewburys@usda.gov | H30: Ireland | I30: Ara | J30: D | K30: 0.5 | L30: 5.97 | M30: 17.91 | N30: Arabica | O30: Dark | P30: =_xlfn.XLOOKUP(orders_final[[#This Row],[Customer ID]], customers!$A$1:$A$1001, customers!$I$1:$I$1001, 0) -> No
A31: RYZ-14633-602 | B31: 43516 | C31: 14158-30713-OB | D31: A-D-1 | E31: 4 | F31: Mozelle Calcutt | G31: mcalcuttt@baidu.com | H31: Ireland | I31: Ara | J31: D | K31: 1 | L31: 9.95 | M31: 39.8 | N31: Arabica | O31: Dark | P31: =_xlfn.XLOOKUP(orders_final[[#This Row],[Customer ID]], customers!$A$1:$A$1001, customers!$I$1:$I$1001, 0) -> Yes
A32: WOQ-36015-429 | B32: 44464 | C32: 51427-89175-QJ | D32: L-M-0.2 | E32: 5 | F32: Adrian Swaine | H32: United States | I32: Lib | J32: M | K32: 0.2 | L32: 4.365 | M32: 21.825 | N32: Liberica | O32: Medium | P32: =_xlfn.XLOOKUP(orders_final[[#This Row],[Customer ID]], customers!$A$1:$A$1001, customers!$I$1:$I$1001, 0) -> No
A33: WOQ-36015-429 | B33: 44464 | C33: 51427-89175-QJ | D33: A-D-0.5 | E33: 6 | F33: Adrian Swaine | H33: United States | I33: Ara | J33: D | K33: 0.5 | L33: 5.97 | M33: 35.82 | N33: Arabica | O33: Dark | P33: =_xlfn.XLOOKUP(orders_final[[#This Row],[Customer ID]], customers!$A$1:$A$1001, customers!$I$1:$I$1001, 0) -> No
A34: WOQ-36015-429 | B34: 44464 | C34: 51427-89175-QJ | D34: L-M-0.5 | E34: 6 | F34: Adrian Swaine | H34: United States | I34: Lib | J34: M | K34: 0.5 | L34: 8.73 | M34: 52.38 | N34: Liberica | O34: Medium | P34: =_xlfn.XLOOKUP(orders_final[[#This Row],[Customer ID]], customers!$A$1:$A$1001, customers!$I$1:$I$1001, 0) -> No
A35: SCT-60553-454 | B35: 44394 | C35: 39123-12846-YJ | D35: L-L-0.2 | E35: 5 | F35: Gallard Gatheral | G35: ggatheralx@123-reg.co.uk | H35: United States | I35: Lib | J35: L | K35: 0.2 | L35: 4.755 | M35: 23.775 | N35: Liberica | O35: Light | P35: =_xlfn.XLOOKUP(orders_final[[#This Row],[Customer ID]], customers!$A$1:$A$1001, customers!$I$1:$I$1001, 0) -> No
A36: GFK-52063-244 | B36: 44011 | C36: 44981-99666-XB | D36: L-L-0.5 | E36: 6 | F36: Una Welberry | G36: uwelberryy@ebay.co.uk | H36: United Kingdom | I36: Lib | J36: L | K36: 0.5 | L36: 9.51 | M36: 57.06 | N36: Liberica | O36: Light | P36: =_xlfn.XLOOKUP(orders_final[[#This Row],[Customer ID]], customers!$A$1:$A$1001, customers!$I$1:$I$1001, 0) -> Yes
A37: AMM-79521-378 | B37: 44348 | C37: 24825-51803-CQ | D37: A-D-0.5 | E37: 6 | F37: Faber Eilhart | G37: feilhartz@who.int | H37: United States | I37: Ara | J37: D | K37: 0.5 | L37: 5.97 | M37: 35.82 | N37: Arabica | O37: Dark | P37: =_xlfn.XLOOKUP(orders_final[[#This Row],[Customer ID]], customers!$A$1:$A$1001, customers!$I$1:$I$1001, 0) -> No
A38: QUQ-90580-772 | B38: 44233 | C38: 77634-13918-GJ | D38: L-M-0.2 | E38: 2 | F38: Zorina Ponting | G38: zponting10@altervista.org | H38: United States | I38: Lib | J38: M | K38: 0.2 | L38: 4.365 | M38: 8.73 | N38: Liberica | O38: Medium | P38: =_xlfn.XLOOKUP(orders_final[[#This Row],[Customer ID]], customers!$A$1:$A$1001, customers!$I$1:$I$1001, 0) -> No
A39: LGD-24408-274 | B39: 43580 | C39: 13694-25001-LX | D39: L-L-0.5 | E39: 3 | F39: Silvio Strase | G39: sstrase11@booking.com | H39: United States | I39: Lib | J39: L | K39: 0.5 | L39: 9.51 | M39: 28.53 | N39: Liberica | O39: Light | P39: =_xlfn.XLOOKUP(orders_final[[#This Row],[Customer ID]], customers!$A$1:$A$1001, customers!$I$1:$I$1001, 0) -> No
A40: HCT-95608-959 | B40: 43946 | C40: 08523-01791-TI | D40: R-M-2.5 | E40: 5 | F40: Dorie de la Tremoille | G40: dde12@unesco.org | H40: United States | I40: Rob | J40: M | K40: 2.5 | L40: 22.885 | M40: 114.425 | N40: Robusta | O40: Medium | P40: =_xlfn.XLOOKUP(orders_final[[#This Row],[Customer ID]], customers!$A$1:$A$1001, customers!$I$1:$I$1001, 0) -> No
A41: OFX-99147-470 | B41: 44524 | C41: 49860-68865-AB | D41: R-M-1 | E41: 6 | F41: Hy Zanetto | H41: United States | I41: Rob | J41: M | K41: 1 | L41: 9.95 | M41: 59.7 | N41: Robusta | O41: Medium | P41: =_xlfn.XLOOKUP(orders_final[[#This Row],[Customer ID]], customers!$A$1:$A$1001, customers!$I$1:$I$1001, 0) -> Yes
A42: LUO-37559-016 | B42: 44305 | C42: 21240-83132-SP | D42: L-M-1 | E42: 3 | F42: Jessica McNess | H42: United States | I42: Lib | J42: M | K42: 1 | L42: 14.55 | M42: 43.65 | N42: Liberica | O42: Medium | P42: =_xlfn.XLOOKUP(orders_final[[#This Row],[Customer ID]], customers!$A$1:$A$1001, customers!$I$1:$I$1001, 0) -> No
A43: XWC-20610-167 | B43: 44749 | C43: 08350-81623-TF | D43: E-D-0.2 | E43: 2 | F43: Lorenzo Yeoland | G43: lyeoland15@pbs.org | H43: United States | I43: Exc | J43: D | K43: 0.2 | L43: 3.645 | M43: 7.29 | N43: Excelsa | O43: Dark | P43: =_xlfn.XLOOKUP(orders_final[[#This Row],[Customer ID]], customers!$A$1:$A$1001, customers!$I$1:$I$1001, 0) -> Yes
A44: GPU-79113-136 | B44: 43607 | C44: 73284-01385-SJ | D44: R-D-0.2 | E44: 3 | F44: Abigail Tolworthy | G44: atolworthy16@toplist.cz | H44: United States | I44: Rob | J44: D | K44: 0.2 | L44: 2.685 | M44: 8.055 | N44: Robusta | O44: Dark | P44: =_xlfn.XLOOKUP(orders_final[[#This Row],[Customer ID]], customers!$A$1:$A$1001, customers!$I$1:$I$1001, 0) -> Yes
A45: ULR-52653-960 | B45: 44473 | C45: 04152-34436-IE | D45: L-L-2.5 | E45: 2 | F45: Maurie Bartol | H45: United States | I45: Lib | J45: L | K45: 2.5 | L45: 36.455 | M45: 72.91 | N45: Liberica | O45: Light | P45: =_xlfn.XLOOKUP(orders_final[[#This Row],[Customer ID]], customers!$A$1:$A$1001, customers!$I$1:$I$1001, 0) -> No
A46: HPI-42308-142 | B46: 43932 | C46: 06631-86965-XP | D46: E-M-0.5 | E46: 2 | F46: Olag Baudassi | G46: obaudassi18@seesaa.net | H46: United States | I46: Exc | J46: M | K46: 0.5 | L46: 8.25 | M46: 16.5 | N46: Excelsa | O46: Medium | P46: =_xlfn.XLOOKUP(orders_final[[#This Row],[Customer ID]], customers!$A$1:$A$1001, customers!$I$1:$I$1001, 0) -> Yes
A47: XHI-30227-581 | B47: 44592 | C47: 54619-08558-ZU | D47: L-D-2.5 | E47: 6 | F47: Petey Kingsbury | G47: pkingsbury19@comcast.net | H47: United States | I47: Lib | J47: D | K47: 2.5 | L47: 29.785 | M47: 178.71 | N47: Liberica | O47: Dark | P47: =_xlfn.XLOOKUP(orders_final[[#This Row],[Customer ID]], customers!$A$1:$A$1001, customers!$I$1:$I$1001, 0) -> No
A48: DJH-05202-380 | B48: 43776 | C48: 85589-17020-CX | D48: E-M-2.5 | E48: 2 | F48: Donna Baskeyfied | H48: United States | I48: Exc | J48: M | K48: 2.5 | L48: 31.625 | M48: 63.25 | N48: Excelsa | O48: Medium | P48: =_xlfn.XLOOKUP(orders_final[[#This Row],[Customer ID]], customers!$A$1:$A$1001, customers!$I$1:$I$1001, 0) -> Yes
A49: VMW-26889-781 | B49: 43644 | C49: 36078-91009-WU | D49: A-L-0.2 | E49: 2 | F49: Arda Curley | G49: acurley1b@hao123.com | H49: United States | I49: Ara | J49: L | K49: 0.2 | L49: 3.885 | M49: 7.77 | N49: Arabica | O49: Light | P49: =_xlfn.XLOOKUP(orders_final[[#This Row],[Customer ID]], customers!$A$1:$A$1001, customers!$I$1:$I$1001, 0) -> Yes
A50: DBU-81099-586 | B50: 44085 | C50: 15770-27099-GX | D50: A-D-2.5 | E50: 4 | F50: Raynor McGilvary | G50: rmcgilvary1c@tamu.edu | H50: United States | I50: Ara | J50: D | K50: 2.5 | L50: 22.885 | M50: 91.54 | N50: Arabica | O50: Dark | P50: =_xlfn.XLOOKUP(orders_final[[#This Row],[Customer ID]], customers!$A$1:$A$1001, customers!$I$1:$I$1001, 0) -> No
A51: PQA-54820-810 | B51: 44790 | C51: 91460-04823-BX | D51: A-L-1 | E51: 3 | F51: Isis Pikett | G51: ipikett1d@xinhuanet.com | H51: United States | I51: Ara | J51: L | K51: 1 | L51: 12.95 | M51: 38.85 | N51: Arabica | O51: Light | P51: =_xlfn.XLOOKUP(orders_final[[#This Row],[Customer ID]], customers!$A$1:$A$1001, customers!$I$1:$I$1001, 0) -> No
A52: XKB-41924-202 | B52: 44792 | C52: 45089-52817-WN | D52: L-D-0.5 | E52: 2 | F52: Inger Bouldon | G52: ibouldon1e@gizmodo.com | H52: United States | I52: Lib | J52: D | K52: 0.5 | L52: 7.77 | M52: 15.54 | N52: Liberica | O52: Dark | P52: =_xlfn.XLOOKUP(orders_final[[#This Row],[Customer ID]], customers!$A$1:$A$1001, customers!$I$1:$I$1001, 0) -> No
A53: DWZ-69106-473 | B53: 43600 | C53: 76447-50326-IC | D53: L-L-2.5 | E53: 4 | F53: Karry Flanders | G53: kflanders1f@over-blog.com | H53: Ireland | I53: Lib | J53: L | K53: 2.5 | L53: 36.455 | M53: 145.82 | N53: Liberica | O53: Light | P53: =_xlfn.XLOOKUP(orders_final[[#This Row],[Customer ID]], customers!$A$1:$A$1001, customers!$I$1:$I$1001, 0) -> Yes
A54: YHV-68700-050 | B54: 43719 | C54: 26333-67911-OL | D54: R-M-0.5 | E54: 5 | F54: Hartley Mattioli | G54: hmattioli1g@webmd.com | H54: United Kingdom | I54: Rob | J54: M | K54: 0.5 | L54: 5.97 | M54: 29.85 | N54: Robusta | O54: Medium | P54: =_xlfn.XLOOKUP(orders_final[[#This Row],[Customer ID]], customers!$A$1:$A$1001, customers!$I$1:$I$1001, 0) -> No
A55: YHV-68700-050 | B55: 43719 | C55: 26333-67911-OL | D55: L-L-2.5 | E55: 2 | F55: Hartley Mattioli | G55: hmattioli1g@webmd.com | H55: United Kingdom | I55: Lib | J55: L | K55: 2.5 | L55: 36.455 | M55: 72.91 | N55: Liberica | O55: Light | P55: =_xlfn.XLOOKUP(orders_final[[#This Row],[Customer ID]], customers!$A$1:$A$1001, customers!$I$1:$I$1001, 0) -> No
A56: KRB-88066-642 | B56: 44271 | C56: 22107-86640-SB | D56: L-M-1 | E56: 5 | F56: Archambault Gillard | G56: agillard1i@issuu.com | H56: United States | I56: Lib | J56: M | K56: 1 | L56: 14.55 | M56: 72.75 | N56: Liberica | O56: Medium | P56: =_xlfn.XLOOKUP(orders_final[[#This Row],[Customer ID]], customers!$A$1:$A$1001, customers!$I$1:$I$1001, 0) -> No
A57: LQU-08404-173 | B57: 44168 | C57: 09960-34242-LZ | D57: L-L-1 | E57: 3 | F57: Salomo Cushworth | H57: United States | I57: Lib | J57: L | K57: 1 | L57: 15.85 | M57: 47.55 | N57: Liberica | O57: Light | P57: =_xlfn.XLOOKUP(orders_final[[#This Row],[Customer ID]], customers!$A$1:$A$1001, customers!$I$1:$I$1001, 0) -> No
A58: CWK-60159-881 | B58: 43857 | C58: 04671-85591-RT | D58: E-D-0.2 | E58: 3 | F58: Theda Grizard | G58: tgrizard1k@odnoklassniki.ru | H58: United States | I58: Exc | J58: D | K58: 0.2 | L58: 3.645 | M58: 10.935 | N58: Excelsa | O58: Dark | P58: =_xlfn.XLOOKUP(orders_final[[#This Row],[Customer ID]], customers!$A$1:$A$1001, customers!$I$1:$I$1001, 0) -> Yes
A59: EEG-74197-843 | B59: 44759 | C59: 25729-68859-UA | D59: E-L-1 | E59: 4 | F59: Rozele Relton | G59: rrelton1l@stanford.edu | H59: United States | I59: Exc | J59: L | K59: 1 | L59: 14.85 | M59: 59.4 | N59: Excelsa | O59: Light | P59: =_xlfn.XLOOKUP(orders_final[[#This Row],[Customer ID]], customers!$A$1:$A$1001, customers!$I$1:$I$1001, 0) -> No
A60: UCZ-59708-525 | B60: 44624 | C60: 05501-86351-NX | D60: L-D-2.5 | E60: 3 | F60: Willa Rolling | H60: United States | I60: Lib | J60: D | K60: 2.5 | L60: 29.785 | M60: 89.355 | N60: Liberica | O60: Dark | P60: =_xlfn.XLOOKUP(orders_final[[#This Row],[Customer ID]], customers!$A$1:$A$1001, customers!$I$1:$I$1001, 0) -> Yes
A61: HUB-47311-849 | B61: 44537 | C61: 04521-04300-OK | D61: L-M-0.5 | E61: 3 | F61: Stanislaus Gilroy | G61: sgilroy1n@eepurl.com | H61: United States | I61: Lib | J61: M | K61: 0.5 | L61: 8.73 | M61: 26.19 | N61: Liberica | O61: Medium | P61: =_xlfn.XLOOKUP(orders_final[[#This Row],[Customer ID]], customers!$A$1:$A$1001, customers!$I$1:$I$1001, 0) -> Yes
A62: WYM-17686-694 | B62: 44252 | C62: 58689-55264-VK | D62: A-D-2.5 | E62: 5 | F62: Correy Cottingham | G62: ccottingham1o@wikipedia.org | H62: United States | I62: Ara | J62: D | K62: 2.5 | L62: 22.885 | M62: 114.425 | N62: Arabica | O62: Dark | P62: =_xlfn.XLOOKUP(orders_final[[#This Row],[Customer ID]], customers!$A$1:$A$1001, customers!$I$1:$I$1001, 0) -> No
A63: ZYQ-15797-695 | B63: 43521 | C63: 79436-73011-MM | D63: R-D-0.5 | E63: 5 | F63: Pammi Endacott | H63: United Kingdom | I63: Rob | J63: D | K63: 0.5 | L63: 5.37 | M63: 26.85 | N63: Robusta | O63: Dark | P63: =_xlfn.XLOOKUP(orders_final[[#This Row],[Customer ID]], customers!$A$1:$A$1001, customers!$I$1:$I$1001, 0) -> Yes
A64: EEJ-16185-108 | B64: 43505 | C64: 65552-60476-KY | D64: L-L-0.2 | E64: 5 | F64: Nona Linklater | H64: United States | I64: Lib | J64: L | K64: 0.2 | L64: 4.755 | M64: 23.775 | N64: Liberica | O64: Light | P64: =_xlfn.XLOOKUP(orders_final[[#This Row],[Customer ID]], customers!$A$1:$A$1001, customers!$I$1:$I$1001, 0) -> Yes
A65: RWR-77888-800 | B65: 43868 | C65: 69904-02729-YS | D65: A-M-0.5 | E65: 1 | F65: Annadiane Dykes | G65: adykes1r@eventbrite.com | H65: United States | I65: Ara | J65: M | K65: 0.5 | L65: 6.75 | M65: 6.75 | N65: Arabica | O65: Medium | P65: =_xlfn.XLOOKUP(orders_final[[#This Row],[Customer ID]], customers!$A$1:$A$1001, customers!$I$1:$I$1001, 0) -> No
A66: LHN-75209-742 | B66: 43913 | C66: 01433-04270-AX | D66: R-M-0.5 | E66: 6 | F66: Felecia Dodgson | H66: United States | I66: Rob | J66: M | K66: 0.5 | L66: 5.97 | M66: 35.82 | N66: Robusta | O66: Medium | P66: =_xlfn.XLOOKUP(orders_final[[#This Row],[Customer ID]], customers!$A$1:$A$1001, customers!$I$1:$I$1001, 0) -> Yes
A67: TIR-71396-998 | B67: 44626 | C67: 14204-14186-LA | D67: R-D-2.5 | E67: 4 | F67: Angelia Cockrem | G67: acockrem1t@engadget.com | H67: United States | I67: Rob | J67: D | K67: 2.5 | L67: 20.585 | M67: 82.34 | N67: Robusta | O67: Dark | P67: =_xlfn.XLOOKUP(orders_final[[#This Row],[Customer ID]], customers!$A$1:$A$1001, customers!$I$1:$I$1001, 0) -> Yes
A68: RXF-37618-213 | B68: 44666 | C68: 32948-34398-HC | D68: R-L-0.5 | E68: 1 | F68: Belvia Umpleby | G68: bumpleby1u@soundcloud.com | H68: United States | I68: Rob | J68: L | K68: 0.5 | L68: 7.17 | M68: 7.17 | N68: Robusta | O68: Light | P68: =_xlfn.XLOOKUP(orders_final[[#This Row],[Customer ID]], customers!$A$1:$A$1001, customers!$I$1:$I$1001, 0) -> Yes
A69: ANM-16388-634 | B69: 44519 | C69: 77343-52608-FF | D69: L-L-0.2 | E69: 2 | F69: Nat Saleway | G69: nsaleway1v@dedecms.com | H69: United States | I69: Lib | J69: L | K69: 0.2 | L69: 4.755 | M69: 9.51 | N69: Liberica | O69: Light | P69: =_xlfn.XLOOKUP(orders_final[[#This Row],[Customer ID]], customers!$A$1:$A$1001, customers!$I$1:$I$1001, 0) -> No
A70: WYL-29300-070 | B70: 43754 | C70: 42770-36274-QA | D70: R-M-0.2 | E70: 1 | F70: Hayward Goulter | G70: hgoulter1w@abc.net.au | H70: United States | I70: Rob | J70: M | K70: 0.2 | L70: 2.985 | M70: 2.985 | N70: Robusta | O70: Medium | P70: =_xlfn.XLOOKUP(orders_final[[#This Row],[Customer ID]], customers!$A$1:$A$1001, customers!$I$1:$I$1001, 0) -> No
A71: JHW-74554-805 | B71: 43795 | C71: 14103-58987-ZU | D71: R-M-1 | E71: 6 | F71: Gay Rizzello | G71: grizzello1x@symantec.com | H71: United Kingdom | I71: Rob | J71: M | K71: 1 | L71: 9.95 | M71: 59.7 | N71: Robusta | O71: Medium | P71: =_xlfn.XLOOKUP(orders_final[[#This Row],[Customer ID]], customers!$A$1:$A$1001, customers!$I$1:$I$1001, 0) -> Yes
A72: KYS-27063-603 | B72: 43646 | C72: 69958-32065-SW | D72: E-L-2.5 | E72: 4 | F72: Shannon List | G72: slist1y@mapquest.com | H72: United States | I72: Exc | J72: L | K72: 2.5 | L72: 34.155 | M72: 136.62 | N72: Excelsa | O72: Light | P72: =_xlfn.XLOOKUP(orders_final[[#This Row],[Customer ID]], customers!$A$1:$A$1001, customers!$I$1:$I$1001, 0) -> No
A73: GAZ-58626-277 | B73: 44200 | C73: 69533-84907-FA | D73: L-L-0.2 | E73: 2 | F73: Shirlene Edmondson | G73: sedmondson1z@theguardian.com | H73: Ireland | I73: Lib | J73: L | K73: 0.2 | L73: 4.755 | M73: 9.51 | N73: Liberica | O73: Light | P73: =_xlfn.XLOOKUP(orders_final[[#This Row],[Customer ID]], customers!$A$1:$A$1001, customers!$I$1:$I$1001, 0) -> No
A74: RPJ-37787-335 | B74: 44131 | C74: 76005-95461-CI | D74: A-M-2.5 | E74: 3 | F74: Aurlie McCarl | H74: United States | I74: Ara | J74: M | K74: 2.5 | L74: 25.875 | M74: 77.625 | N74: Arabica | O74: Medium | P74: =_xlfn.XLOOKUP(orders_final[[#This Row],[Customer ID]], customers!$A$1:$A$1001, customers!$I$1:$I$1001, 0) -> No
A75: LEF-83057-763 | B75: 44362 | C75: 15395-90855-VB | D75: L-M-0.2 | E75: 5 | F75: Alikee Carryer | H75: United States | I75: Lib | J75: M | K75: 0.2 | L75: 4.365 | M75: 21.825 | N75: Liberica | O75: Medium | P75: =_xlfn.XLOOKUP(orders_final[[#This Row],[Customer ID]], customers!$A$1:$A$1001, customers!$I$1:$I$1001, 0) -> Yes
A76: RPW-36123-215 | B76: 44396 | C76: 80640-45811-LB | D76: E-L-0.5 | E76: 2 | F76: Jennifer Rangall | G76: jrangall22@newsvine.com | H76: United States | I76: Exc | J76: L | K76: 0.5 | L76: 8.91 | M76: 17.82 | N76: Excelsa | O76: Light | P76: =_xlfn.XLOOKUP(orders_final[[#This Row],[Customer ID]], customers!$A$1:$A$1001, customers!$I$1:$I$1001, 0) -> Yes
A77: WLL-59044-117 | B77: 44400 | C77: 28476-04082-GR | D77: R-D-1 | E77: 6 | F77: Kipper Boorn | G77: kboorn23@ezinearticles.com | H77: Ireland | I77: Rob | J77: D | K77: 1 | L77: 8.95 | M77: 53.7 | N77: Robusta | O77: Dark | P77: =_xlfn.XLOOKUP(orders_final[[#This Row],[Customer ID]], customers!$A$1:$A$1001, customers!$I$1:$I$1001, 0) -> Yes
A78: AWT-22827-563 | B78: 43855 | C78: 12018-75670-EU | D78: R-L-0.2 | E78: 1 | F78: Melania Beadle | H78: Ireland | I78: Rob | J78: L | K78: 0.2 | L78: 3.585 | M78: 3.585 | N78: Robusta | O78: Light | P78: =_xlfn.XLOOKUP(orders_final[[#This Row],[Customer ID]], customers!$A$1:$A$1001, customers!$I$1:$I$1001, 0) -> Yes
A79: QLM-07145-668 | B79: 43594 | C79: 86437-17399-FK | D79: E-D-0.2 | E79: 2 | F79: Colene Elgey | G79: celgey25@webs.com | H79: United States | I79: Exc | J79: D | K79: 0.2 | L79: 3.645 | M79: 7.29 | N79: Excelsa | O79: Dark | P79: =_xlfn.XLOOKUP(orders_final[[#This Row],[Customer ID]], customers!$A$1:$A$1001, customers!$I$1:$I$1001, 0) -> No
A80: HVQ-64398-930 | B80: 43920 | C80: 62979-53167-ML | D80: A-M-0.5 | E80: 6 | F80: Lothaire Mizzi | G80: lmizzi26@rakuten.co.jp | H80: United States | I80: Ara | J80: M | K80: 0.5 | L80: 6.75 | M80: 40.5 | N80: Arabica | O80: Medium | P80: =_xlfn.XLOOKUP(orders_final[[#This Row],[Customer ID]], customers!$A$1:$A$1001, customers!$I$1:$I$1001, 0) -> Yes
A81: WRT-40778-247 | B81: 44633 | C81: 54810-81899-HL | D81: R-L-1 | E81: 4 | F81: Cletis Giacomazzo | G81: cgiacomazzo27@jigsy.com | H81: United States | I81: Rob | J81: L | K81: 1 | L81: 11.95 | M81: 47.8 | N81: Robusta | O81: Light | P81: =_xlfn.XLOOKUP(orders_final[[#This Row],[Customer ID]], customers!$A$1:$A$1001, customers!$I$1:$I$1001, 0) -> No
A82: SUB-13006-125 | B82: 43572 | C82: 26103-41504-IB | D82: A-L-0.5 | E82: 5 | F82: Ami Arnow | G82: aarnow28@arizona.edu | H82: United States | I82: Ara | J82: L | K82: 0.5 | L82: 7.77 | M82: 38.85 | N82: Arabica | O82: Light | P82: =_xlfn.XLOOKUP(orders_final[[#This Row],[Customer ID]], customers!$A$1:$A$1001, customers!$I$1:$I$1001, 0) -> Yes
A83: CQM-49696-263 | B83: 43763 | C83: 76534-45229-SG | D83: L-L-2.5 | E83: 3 | F83: Sheppard Yann | G83: syann29@senate.gov | H83: United States | I83: Lib | J83: L | K83: 2.5 | L83: 36.455 | M83: 109.365 | N83: Liberica | O83: Light | P83: =_xlfn.XLOOKUP(orders_final[[#This Row],[Customer ID]], customers!$A$1:$A$1001, customers!$I$1:$I$1001, 0) -> Yes
A84: KXN-85094-246 | B84: 43721 | C84: 81744-27332-RR | D84: L-M-2.5 | E84: 3 | F84: Bunny Naulls | G84: bnaulls2a@tiny.cc | H84: Ireland | I84: Lib | J84: M | K84: 2.5 | L84: 33.465 | M84: 100.395 | N84: Liberica | O84: Medium | P84: =_xlfn.XLOOKUP(orders_final[[#This Row],[Customer ID]], customers!$A$1:$A$1001, customers!$I$1:$I$1001, 0) -> Yes
A85: XOQ-12405-419 | B85: 43933 | C85: 91513-75657-PH | D85: R-D-2.5 | E85: 4 | F85: Hally Lorait | H85: United States | I85: Rob | J85: D | K85: 2.5 | L85: 20.585 | M85: 82.34 | N85: Robusta | O85: Dark | P85: =_xlfn.XLOOKUP(orders_final[[#This Row],[Customer ID]], customers!$A$1:$A$1001, customers!$I$1:$I$1001, 0) -> Yes
A86: HYF-10254-369 | B86: 43783 | C86: 30373-66619-CB | D86: L-L-0.5 | E86: 1 | F86: Zaccaria Sherewood | G86: zsherewood2c@apache.org | H86: United States | I86: Lib | J86: L | K86: 0.5 | L86: 9.51 | M86: 9.51 | N86: Liberica | O86: Light | P86: =_xlfn.XLOOKUP(orders_final[[#This Row],[Customer ID]], customers!$A$1:$A$1001, customers!$I$1:$I$1001, 0) -> No
A87: XXJ-47000-307 | B87: 43664 | C87: 31582-23562-FM | D87: A-L-2.5 | E87: 3 | F87: Jeffrey Dufaire | G87: jdufaire2d@fc2.com | H87: United States | I87: Ara | J87: L | K87: 2.5 | L87: 29.785 | M87: 89.355 | N87: Arabica | O87: Light | P87: =_xlfn.XLOOKUP(orders_final[[#This Row],[Customer ID]], customers!$A$1:$A$1001, customers!$I$1:$I$1001, 0) -> No
A88: XXJ-47000-307 | B88: 43664 | C88: 31582-23562-FM | D88: A-D-0.2 | E88: 4 | F88: Jeffrey Dufaire | G88: jdufaire2d@fc2.com | H88: United States | I88: Ara | J88: D | K88: 0.2 | L88: 2.985 | M88: 11.94 | N88: Arabica | O88: Dark | P88: =_xlfn.XLOOKUP(orders_final[[#This Row],[Customer ID]], customers!$A$1:$A$1001, customers!$I$1:$I$1001, 0) -> No
A89: ZDK-82166-357 | B89: 44289 | C89: 81431-12577-VD | D89: A-M-1 | E89: 3 | F89: Beitris Keaveney | G89: bkeaveney2f@netlog.com | H89: United States | I89: Ara | J89: M | K89: 1 | L89: 11.25 | M89: 33.75 | N89: Arabica | O89: Medium | P89: =_xlfn.XLOOKUP(orders_final[[#This Row],[Customer ID]], customers!$A$1:$A$1001, customers!$I$1:$I$1001, 0) -> No
A90: IHN-19982-362 | B90: 44284 | C90: 68894-91205-MP | D90: R-L-1 | E90: 3 | F90: Elna Grise | G90: egrise2g@cargocollective.com | H90: United States | I90: Rob | J90: L | K90: 1 | L90: 11.95 | M90: 35.85 | N90: Robusta | O90: Light | P90: =_xlfn.XLOOKUP(orders_final[[#This Row],[Customer ID]], customers!$A$1:$A$1001, customers!$I$1:$I$1001, 0) -> No
A91: VMT-10030-889 | B91: 44545 | C91: 87602-55754-VN | D91: A-L-1 | E91: 6 | F91: Torie Gottelier | G91: tgottelier2h@vistaprint.com | H91: United States | I91: Ara | J91: L | K91: 1 | L91: 12.95 | M91: 77.7 | N91: Arabica | O91: Light | P91: =_xlfn.XLOOKUP(orders_final[[#This Row],[Customer ID]], customers!$A$1:$A$1001, customers!$I$1:$I$1001, 0) -> No
A92: NHL-11063-100 | B92: 43971 | C92: 39181-35745-WH | D92: A-L-1 | E92: 4 | F92: Loydie Langlais | H92: Ireland | I92: Ara | J92: L | K92: 1 | L92: 12.95 | M92: 51.8 | N92: Arabica | O92: Light | P92: =_xlfn.XLOOKUP(orders_final[[#This Row],[Customer ID]], customers!$A$1:$A$1001, customers!$I$1:$I$1001, 0) -> Yes
A93: ROV-87448-086 | B93: 44137 | C93: 30381-64762-NG | D93: A-M-2.5 | E93: 4 | F93: Adham Greenhead | G93: agreenhead2j@dailymail.co.uk | H93: United States | I93: Ara | J93: M | K93: 2.5 | L93: 25.875 | M93: 103.5 | N93: Arabica | O93: Medium | P93: =_xlfn.XLOOKUP(orders_final[[#This Row],[Customer ID]], customers!$A$1:$A$1001, customers!$I$1:$I$1001, 0) -> No
A94: DGY-35773-612 | B94: 44037 | C94: 17503-27693-ZH | D94: E-L-1 | E94: 3 | F94: Hamish MacSherry | H94: United States | I94: Exc | J94: L | K94: 1 | L94: 14.85 | M94: 44.55 | N94: Excelsa | O94: Light | P94: =_xlfn.XLOOKUP(orders_final[[#This Row],[Customer ID]], customers!$A$1:$A$1001, customers!$I$1:$I$1001, 0) -> Yes
A95: YWH-50638-556 | B95: 43538 | C95: 89442-35633-HJ | D95: E-L-0.5 | E95: 4 | F95: Else Langcaster | G95: elangcaster2l@spotify.com | H95: United Kingdom | I95: Exc | J95: L | K95: 0.5 | L95: 8.91 | M95: 35.64 | N95: Excelsa | O95: Light | P95: =_xlfn.XLOOKUP(orders_final[[#This Row],[Customer ID]], customers!$A$1:$A$1001, customers!$I$1:$I$1001, 0) -> Yes
A96: ISL-11200-600 | B96: 44014 | C96: 13654-85265-IL | D96: A-D-0.2 | E96: 6 | F96: Rudy Farquharson | H96: Ireland | I96: Ara | J96: D | K96: 0.2 | L96: 2.985 | M96: 17.91 | N96: Arabica | O96: Dark | P96: =_xlfn.XLOOKUP(orders_final[[#This Row],[Customer ID]], customers!$A$1:$A$1001, customers!$I$1:$I$1001, 0) -> Yes
A97: LBZ-75997-047 | B97: 43816 | C97: 40946-22090-FP | D97: A-M-2.5 | E97: 6 | F97: Norene Magauran | G97: nmagauran2n@51.la | H97: United States | I97: Ara | J97: M | K97: 2.5 | L97: 25.875 | M97: 155.25 | N97: Arabica | O97: Medium | P97: =_xlfn.XLOOKUP(orders_final[[#This Row],[Customer ID]], customers!$A$1:$A$1001, customers!$I$1:$I$1001, 0) -> No
A98: EUH-08089-954 | B98: 44171 | C98: 29050-93691-TS | D98: A-D-0.2 | E98: 2 | F98: Vicki Kirdsch | G98: vkirdsch2o@google.fr | H98: United States | I98: Ara | J98: D | K98: 0.2 | L98: 2.985 | M98: 5.97 | N98: Arabica | O98: Dark | P98: =_xlfn.XLOOKUP(orders_final[[#This Row],[Customer ID]], customers!$A$1:$A$1001, customers!$I$1:$I$1001, 0) -> No
A99: BLD-12227-251 | B99: 44259 | C99: 64395-74865-WF | D99: A-M-0.5 | E99: 2 | F99: Ilysa Whapple | G99: iwhapple2p@com.com | H99: United States | I99: Ara | J99: M | K99: 0.5 | L99: 6.75 | M99: 13.5 | N99: Arabica | O99: Medium | P99: =_xlfn.XLOOKUP(orders_final[[#This Row],[Customer ID]], customers!$A$1:$A$1001, customers!$I$1:$I$1001, 0) -> No
A100: OPY-30711-853 | B100: 44394 | C100: 81861-66046-SU | D100: A-D-0.2 | E100: 1 | F100: Ruy Cancellieri | H100: Ireland | I100: Ara | J100: D | K100: 0.2 | L100: 2.985 | M100: 2.985 | N100: Arabica | O100: Dark | P100: =_xlfn.XLOOKUP(orders_final[[#This Row],[Customer ID]], customers!$A$1:$A$1001, customers!$I$1:$I$1001, 0) -> No
A101: DBC-44122-300 | B101: 44139 | C101: 13366-78506-KP | D101: L-M-0.2 | E101: 3 | F101: Aube Follett | H101: United States | I101: Lib | J101: M | K101: 0.2 | L101: 4.365 | M101: 13.095 | N101: Liberica | O101: Medium | P101: =_xlfn.XLOOKUP(orders_final[[#This Row],[Customer ID]], customers!$A$1:$A$1001, customers!$I$1:$I$1001, 0) -> Yes
A102: FJQ-60035-234 | B102: 44291 | C102: 08847-29858-HN | D102: A-L-0.2 | E102: 2 | F102: Rudiger Di Bartolomeo | H102: United States | I102: Ara | J102: L | K102: 0.2 | L102: 3.885 | M102: 7.77 | N102: Arabica | O102: Light | P102: =_xlfn.XLOOKUP(orders_final[[#This Row],[Customer ID]], customers!$A$1:$A$1001, customers!$I$1:$I$1001, 0) -> Yes
A103: HSF-66926-425 | B103: 43891 | C103: 00539-42510-RY | D103: L-D-2.5 | E103: 5 | F103: Nickey Youles | G103: nyoules2t@reference.com | H103: Ireland | I103: Lib | J103: D | K103: 2.5 | L103: 29.785 | M103: 148.925 | N103: Liberica | O103: Dark | P103: =_xlfn.XLOOKUP(orders_final[[#This Row],[Customer ID]], customers!$A$1:$A$1001, customers!$I$1:$I$1001, 0) -> Yes
A104: LQG-41416-375 | B104: 44488 | C104: 45190-08727-NV | D104: L-D-1 | E104: 3 | F104: Dyanna Aizikovitz | G104: daizikovitz2u@answers.com | H104: Ireland | I104: Lib | J104: D | K104: 1 | L104: 12.95 | M104: 38.85 | N104: Liberica | O104: Dark | P104: =_xlfn.XLOOKUP(orders_final[[#This Row],[Customer ID]], customers!$A$1:$A$1001, customers!$I$1:$I$1001, 0) -> Yes
...

Sheet Total_sales
A3: Sum of Sales | C3: Coffee Type Name
A4: Years (Order Date) | B4: Months (Order Date) | C4: Arabica | D4: Excelsa | E4: Liberica | F4: Robusta | G4: Grand Total
A5: 2019 | B5: Jan | C5: 186.855 | D5: 305.97 | E5: 213.16 | F5: 123 | G5: 828.985
B6: Feb | C6: 251.965 | D6: 129.46 | E6: 434.04 | F6: 171.94 | G6: 987.405
B7: Mar | C7: 224.945 | D7: 349.12 | E7: 321.04 | F7: 126.035 | G7: 1021.14
B8: Apr | C8: 307.12 | D8: 681.075 | E8: 533.705 | F8: 158.85 | G8: 1680.75
B9: May | C9: 53.665 | D9: 83.025 | E9: 193.835 | F9: 68.04 | G9: 398.565
B10: Jun | C10: 163.02 | D10: 678.36 | E10: 171.045 | F10: 372.255 | G10: 1384.68
B11: Jul | C11: 345.02 | D11: 273.87 | E11: 184.13 | F11: 201.115 | G11: 1004.135
B12: Aug | C12: 334.89 | D12: 70.95 | E12: 134.23 | F12: 166.275 | G12: 706.345
B13: Sep | C13: 178.71 | D13: 166.1 | E13: 439.31 | F13: 492.9 | G13: 1277.02
B14: Oct | C14: 301.985 | D14: 153.765 | E14: 215.555 | F14: 213.665 | G14: 884.97
B15: Nov | C15: 312.835 | D15: 63.25 | E15: 350.895 | F15: 96.405 | G15: 823.385
B16: Dec | C16: 265.62 | D16: 526.515 | E16: 187.06 | F16: 210.59 | G16: 1189.785
A17: 2020 | B17: Jan | C17: 47.25 | D17: 65.805 | E17: 274.675 | F17: 179.22 | G17: 566.95
B18: Feb | C18: 745.45 | D18: 428.885 | E18: 194.175 | F18: 429.83 | G18: 1798.34
B19: Mar | C19: 130.47 | D19: 271.485 | E19: 281.205 | F19: 231.63 | G19: 914.79
B20: Apr | C20: 27 | D20: 347.26 | E20: 147.51 | F20: 240.04 | G20: 761.81
B21: May | C21: 255.115 | D21: 541.73 | E21: 83.43 | F21: 59.08 | G21: 939.355
B22: Jun | C22: 584.79 | D22: 357.43 | E22: 355.34 | F22: 140.88 | G22: 1438.44
B23: Jul | C23: 430.62 | D23: 227.425 | E23: 236.315 | F23: 414.585 | G23: 1308.945
B24: Aug | C24: 22.5 | D24: 77.72 | E24: 60.5 | F24: 139.68 | G24: 300.4
B25: Sep | C25: 126.15 | D25: 195.11 | E25: 89.13 | F25: 302.66 | G25: 713.05
B26: Oct | C26: 376.03 | D26: 523.24 | E26: 440.965 | F26: 174.47 | G26: 1514.705
B27: Nov | C27: 515.18 | D27: 142.56 | E27: 347.04 | F27: 104.085 | G27: 1108.865
B28: Dec | C28: 95.86 | D28: 484.76 | E28: 94.17 | F28: 77.105 | G28: 751.895
A29: 2021 | B29: Jan | C29: 258.345 | D29: 139.625 | E29: 279.52 | F29: 160.195 | G29: 837.685
B30: Feb | C30: 342.2 | D30: 284.25 | E30: 251.83 | F30: 80.55 | G30: 958.83
B31: Mar | C31: 418.305 | D31: 468.125 | E31: 405.055 | F31: 253.155 | G31: 1544.64
B32: Apr | C32: 102.33 | D32: 242.14 | E32: 554.875 | F32: 106.24 | G32: 1005.585
B33: May | C33: 234.72 | D33: 133.08 | E33: 267.2 | F33: 272.69 | G33: 907.69
B34: Jun | C34: 430.39 | D34: 136.205 | E34: 209.6 | F34: 88.335 | G34: 864.53
B35: Jul | C35: 109.005 | D35: 393.575 | E35: 61.035 | F35: 199.49 | G35: 763.105
B36: Aug | C36: 287.525 | D36: 288.67 | E36: 125.58 | F36: 374.135 | G36: 1075.91
B37: Sep | C37: 840.93 | D37: 409.875 | E37: 171.33 | F37: 221.44 | G37: 1643.575
B38: Oct | C38: 299.07 | D38: 260.325 | E38: 584.64 | F38: 256.365 | G38: 1400.4
B39: Nov | C39: 323.325 | D39: 565.57 | E39: 537.81 | F39: 189.475 | G39: 1616.18
B40: Dec | C40: 399.485 | D40: 148.2 | E40: 388.22 | F40: 212.075 | G40: 1147.98
A41: 2022 | B41: Jan | C41: 112.695 | D41: 166.32 | E41: 843.715 | F41: 146.685 | G41: 1269.415
B42: Feb | C42: 114.88 | D42: 133.815 | E42: 91.175 | F42: 53.76 | G42: 393.63
B43: Mar | C43: 277.76 | D43: 175.41 | E43: 462.51 | F43: 399.525 | G43: 1315.205
B44: Apr | C44: 197.895 | D44: 289.755 | E44: 88.545 | F44: 200.255 | G44: 776.45
B45: May | C45: 193.115 | D45: 212.495 | E45: 292.29 | F45: 304.47 | G45: 1002.37
B46: Jun | C46: 179.79 | D46: 426.2 | E46: 170.09 | F46: 379.31 | G46: 1155.39
B47: Jul | C47: 247.29 | D47: 246.685 | E47: 271.055 | F47: 141.7 | G47: 906.73
B48: Aug | C48: 116.395 | D48: 41.25 | E48: 15.54 | F48: 71.06 | G48: 244.245
A49: Grand Total | C49: 11768.495 | D49: 12306.44 | E49: 12054.075 | F49: 9005.245 | G49: 45134.255

Sheet Country Bar Chart
A3: Country | B3: Sum of Sales
A4: United Kingdom | B4: 2798.505
A5: Ireland | B5: 6696.865
A6: United States | B6: 35638.885
A7: Grand Total | B7: 45134.255

Sheet Top Customers
A3: Customer Name | B3: Sum of Sales
A4: Don Flintiff | B4: 278.01
A5: Nealson Cuttler | B5: 281.675
A6: Terri Farra | B6: 289.11
A7: Brenn Dundredge | B7: 307.045
A8: Allis Wilmore | B8: 317.07
A9: Grand Total | B9: 1472.91

Sheet Dashboard

Sheet ORDERS
